freeproxy_cn/__init__.py
freeproxy_cn/core/__init__.py
freeproxy_cn/core/channel.py
freeproxy_cn/core/engine.py
freeproxy_cn/core/request.py
freeproxy_cn/site/I337.py
freeproxy_cn/site/__init__.py
freeproxy_cn/site/cool.py
freeproxy_cn/site/crossin.py
freeproxy_cn/site/eight9.py
freeproxy_cn/site/freeip.py
freeproxy_cn/site/ip3366.py
freeproxy_cn/site/iphai.py
freeproxy_cn/site/ipjiang.py
freeproxy_cn/site/kuai.py
freeproxy_cn/site/proxydocker.py
freeproxy_cn/site/seofang.py
freeproxy_cn/site/super.py
freeproxy_cn/site/xiaosu.py
freeproxy_cn/site/xici.py
freeproxy_cn/site/xroxy.py
freeproxy_cn/util/__init__.py
freeproxy_cn/util/pipe.py
freeproxy_cn-1.4.1.dist-info/LICENSE
freeproxy_cn-1.4.1.dist-info/METADATA
freeproxy_cn-1.4.1.dist-info/WHEEL
freeproxy_cn-1.4.1.dist-info/top_level.txt
freeproxy_cn-1.4.1.dist-info/RECORD
