Metadata-Version: 2.1
Name: freeproxy-cn
Version: 1.4.1
Summary: .. figure:: https://img.shields.io/pypi/pyversions/cuckoopy.svg
Requires-Dist: lxml
Requires-Dist: aiohttp
Requires-Dist: logzero
Requires-Dist: redis
Requires-Dist: dummy-useragent
Requires-Dist: python-dateutil
